PyDB/__init__.py
PyDB/db/__init__.py
PyDB/db/economy_db.py
PyDB/db/errors.py
PyDB/db/level_db.py
PyDB/db/warns_db.py
PyDcDB-0.4.1.dist-info/LICENSE.txt
PyDcDB-0.4.1.dist-info/METADATA
PyDcDB-0.4.1.dist-info/WHEEL
PyDcDB-0.4.1.dist-info/top_level.txt
PyDcDB-0.4.1.dist-info/RECORD
