Metadata-Version: 2.1
Name: PyDcDB
Version: 0.4.1
Summary: UNKNOWN
Author: Dark-Light
Author-email: darklight02014@gmail.com
License: GNU
Keywords: database sqlite3
Platform: UNKNOWN
License-File: LICENSE.txt
Requires-Dist: aiosqlite
